{"trial_id": "0", "hyperparameters": {"space": [{"class_name": "Int", "config": {"name": "num_layers", "default": null, "conditions": [], "min_value": 1, "max_value": 5, "step": 1, "sampling": "linear"}}, {"class_name": "Float", "config": {"name": "dropout_rate", "default": 0.0, "conditions": [], "min_value": 0.0, "max_value": 0.3, "step": 0.005, "sampling": "linear"}}, {"class_name": "Int", "config": {"name": "units_0", "default": null, "conditions": [], "min_value": 10, "max_value": 400, "step": 5, "sampling": "linear"}}, {"class_name": "Int", "config": {"name": "units_1", "default": null, "conditions": [], "min_value": 10, "max_value": 400, "step": 5, "sampling": "linear"}}, {"class_name": "Int", "config": {"name": "batch_size", "default": null, "conditions": [], "min_value": 50, "max_value": 200, "step": 10, "sampling": "linear"}}], "values": {"num_layers": 2, "dropout_rate": 0.21, "units_0": 355, "units_1": 10, "batch_size": 50}}, "metrics": {"metrics": {"loss": {"direction": "min", "observations": [{"value": [0.029104571789503098], "step": 0}]}, "mean_absolute_error": {"direction": "min", "observations": [{"value": [0.3374514579772949], "step": 0}]}, "mean_squared_error": {"direction": "min", "observations": [{"value": [0.19057267904281616], "step": 0}]}, "val_loss": {"direction": "min", "observations": [{"value": [0.022501502186059952], "step": 0}]}, "val_mean_absolute_error": {"direction": "min", "observations": [{"value": [0.27053433656692505], "step": 0}]}, "val_mean_squared_error": {"direction": "min", "observations": [{"value": [0.12316172569990158], "step": 0}]}}}, "score": 0.022501502186059952, "best_step": 0, "status": "COMPLETED", "message": null}